{
  "date": "2026-04-12",
  "generated_at": "2026-05-03T02:45:43.240052Z",
  "top_events": [
    {
      "rank": 1,
      "event_id": "sba_comm-2026-04-12-034",
      "importance_score": 0.75,
      "importance_reasons": [
        "涉及財報"
      ],
      "title": "What You Need to Know Ahead of SBA Communications' Earnings Release - Yahoo Finance",
      "companies": [
        "sba_comm"
      ],
      "related": {
        "customers": [],
        "suppliers": []
      },
      "topics": [
        "earnings"
      ],
      "sentiment": {
        "label": "neutral",
        "score": 0.0
      },
      "source_url": null
    },
    {
      "rank": 2,
      "event_id": "sba_comm-2026-04-12-035",
      "importance_score": 0.75,
      "importance_reasons": [
        "涉及財報"
      ],
      "title": "SBA Communications Shares Undergo Earnings Scrutiny: Will the Acquisition Premium Be Warranted? - Bitget",
      "companies": [
        "sba_comm"
      ],
      "related": {
        "customers": [],
        "suppliers": []
      },
      "topics": [
        "earnings"
      ],
      "sentiment": {
        "label": "neutral",
        "score": 0.0
      },
      "source_url": null
    },
    {
      "rank": 3,
      "event_id": "sba_comm-2026-04-12-036",
      "importance_score": 0.75,
      "importance_reasons": [
        "涉及財報"
      ],
      "title": "SBA Communications Earnings Preview: Analysts Expect FFO Dip - National Today",
      "companies": [
        "sba_comm"
      ],
      "related": {
        "customers": [],
        "suppliers": []
      },
      "topics": [
        "earnings"
      ],
      "sentiment": {
        "label": "neutral",
        "score": 0.0
      },
      "source_url": null
    },
    {
      "rank": 4,
      "event_id": "sba_comm-2026-04-12-014",
      "importance_score": 0.75,
      "importance_reasons": [
        "涉及財報"
      ],
      "title": "What You Need to Know Ahead of SBA Communications' Earnings Release - Barchart.com",
      "companies": [
        "sba_comm"
      ],
      "related": {
        "customers": [],
        "suppliers": []
      },
      "topics": [
        "earnings"
      ],
      "sentiment": {
        "label": "neutral",
        "score": 0.0
      },
      "source_url": null
    }
  ],
  "anomalies": [],
  "topic_trends": {
    "earnings": {
      "today": 4,
      "7d_avg": 0,
      "30d_avg": 0,
      "yoy_same_week": null,
      "trend": "new",
      "consecutive_weeks_rising": 0,
      "sentiment_today": 0.0,
      "sentiment_7d_avg": null
    }
  },
  "supply_chain_activity": [],
  "stats": {
    "total_events": 4,
    "sentiment_distribution": {
      "positive": 0,
      "neutral": 4,
      "negative": 0
    },
    "top_companies": [
      {
        "id": "sba_comm",
        "count": 4
      }
    ],
    "top_topics": [
      {
        "id": "earnings",
        "count": 4
      }
    ]
  }
}